[
  {
    "src": "images/prepped/aerial/mountain.jpeg",
    "alt": "mountain",
    "category": "aerial"
  },
  {
    "src": "images/prepped/homepage/Loft Layout.jpeg",
    "alt": "Loft Layout",
    "category": "homepage"
  },
  {
    "src": "images/prepped/nature/village landscape pic.jpg",
    "alt": "village landscape pic",
    "category": "nature"
  },
  {
    "src": "images/prepped/prepped/Fireplace.jpeg",
    "alt": "Fireplace",
    "category": "prepped"
  },
  {
    "src": "images/prepped/prepped/Loft Layout.jpeg",
    "alt": "Loft Layout",
    "category": "prepped"
  },
  {
    "src": "images/prepped/prepped/kitchen.jpeg",
    "alt": "kitchen",
    "category": "prepped"
  },
  {
    "src": "images/prepped/prepped/mountain.jpeg",
    "alt": "mountain",
    "category": "prepped"
  },
  {
    "src": "images/prepped/prepped/village landscape pic.jpg",
    "alt": "village landscape pic",
    "category": "prepped"
  },
  {
    "src": "images/prepped/urban/Fireplace.jpeg",
    "alt": "Fireplace",
    "category": "urban"
  },
  {
    "src": "images/prepped/urban/kitchen.jpeg",
    "alt": "kitchen",
    "category": "urban"
  }
]